conjugate_prior/__init__.py
conjugate_prior/beta.py
conjugate_prior/dirichlet.py
conjugate_prior/gamma.py
conjugate_prior/invgamma.py
conjugate_prior/normal.py
conjugate_prior/prior.py
conjugate_prior-0.85.dist-info/LICENSE
conjugate_prior-0.85.dist-info/METADATA
conjugate_prior-0.85.dist-info/WHEEL
conjugate_prior-0.85.dist-info/top_level.txt
conjugate_prior-0.85.dist-info/RECORD
