Metadata-Version: 2.1
Name: conjugate_prior
Version: 0.85
Summary: Bayesian Statistics conjugate prior distributions
Home-page: https://github.com/argmaxml/conjugate_prior
Author: Uri Goren
Author-email: conjugate@argmaxml.com
Keywords: conjugate,bayesian,stats,statistics,bayes,distribution,probability,hypothesis,modelling,thompson sampling
License-File: LICENSE
Requires-Dist: setuptools
Requires-Dist: scipy
Requires-Dist: numpy
Requires-Dist: matplotlib
